jsonfile.py
jsonfile-1.0.dist-info/WHEEL
jsonfile-1.0.dist-info/METADATA
jsonfile-1.0.dist-info/RECORD
