Metadata-Version: 1.2
Name: jsonfile
Version: 1.0
Summary: jsonfile - incrementally write files in JSON format.
Home-page: https://github.com/tgs/jsonfile
License: UNKNOWN
Author: Thomas Smith
Author-email: smithtg@ncbi.nlm.nih.gov
Requires-Python: >=3
Classifier: License :: Public Domain
Classifier: Intended Audience :: Developers
Classifier: Programming Language :: Python :: 3
Requires-Dist: enum34; python_version < 3.4
